ai_models_fourcastnet_gfs/__init__.py
ai_models_fourcastnet_gfs/afnonet.py
ai_models_fourcastnet_gfs/model.py
ai_models_fourcastnet_gfs-0.0.2.dist-info/LICENSE
ai_models_fourcastnet_gfs-0.0.2.dist-info/LICENSE_fourcastnet
ai_models_fourcastnet_gfs-0.0.2.dist-info/METADATA
ai_models_fourcastnet_gfs-0.0.2.dist-info/WHEEL
ai_models_fourcastnet_gfs-0.0.2.dist-info/entry_points.txt
ai_models_fourcastnet_gfs-0.0.2.dist-info/top_level.txt
ai_models_fourcastnet_gfs-0.0.2.dist-info/zip-safe
ai_models_fourcastnet_gfs-0.0.2.dist-info/RECORD
