Metadata-Version: 2.1
Name: ai-models-fourcastnet-gfs
Version: 0.0.2
Summary: An ai-models plugin to run FourCastNet
Home-page: https://github.com/jacob-radford/ai-models-fourcastnet-gfs
Author: Jacob Radford
Author-email: jacob.t.radford@gmail.com
License: Apache License Version 2.0
Keywords: tool
Classifier: Development Status :: 3 - Alpha
Classifier: Intended Audience :: Developers
Classifier: License :: OSI Approved :: Apache Software License
Classifier: Programming Language :: Python :: 3
Classifier: Programming Language :: Python :: 3.9
Classifier: Programming Language :: Python :: 3.10
Classifier: Programming Language :: Python :: 3.11
Classifier: Programming Language :: Python :: Implementation :: CPython
Classifier: Programming Language :: Python :: Implementation :: PyPy
Classifier: Operating System :: OS Independent
License-File: LICENSE
License-File: LICENSE_fourcastnet
Requires-Dist: torch >=2.0.0
Requires-Dist: timm >=0.6.13
Requires-Dist: einops >=0.6.0
Requires-Dist: ruamel.yaml >=0.17.21
